README.md
setup.cfg
setup.py
dtk/__init__.py
dtk/utils.py
dtk.egg-info/PKG-INFO
dtk.egg-info/SOURCES.txt
dtk.egg-info/dependency_links.txt
dtk.egg-info/not-zip-safe
dtk.egg-info/requires.txt
dtk.egg-info/top_level.txt
dtk/filesystem/__init__.py
dtk/filesystem/filtering.py
dtk/media/__init__.py
dtk/metrics/__init__.py
dtk/metrics/image.py
dtk/metrics/signal.py
dtk/nn/__init__.py
dtk/nn/activations.py
dtk/nn/loss.py
dtk/nn/modules.py
dtk/nn/utils.py
dtk/nn/temporal/__init__.py
dtk/nn/temporal/attention.py
dtk/nn/temporal/conformer.py
dtk/nn/temporal/convolution.py
dtk/nn/temporal/embedding.py
dtk/nn/temporal/encoder.py
dtk/nn/temporal/encoder_layer.py
dtk/nn/temporal/layer_norm.py
dtk/nn/temporal/multi_layer_conv.py
dtk/nn/temporal/positionwise_feed_forward.py
dtk/nn/temporal/repeat.py
dtk/nn/temporal/subsampling.py
dtk/speech/__init__.py
dtk/speech/voice_detection.py
dtk/transforms/__init__.py
dtk/transforms/audio.py
dtk/transforms/landmarks.py
dtk/transforms/video.py